ohheycrypto/__init__.py
ohheycrypto/__version__.py
ohheycrypto/bot.py
ohheycrypto/cli.py
ohheycrypto/config/__init__.py
ohheycrypto/config/settings.py
ohheycrypto/database/__init__.py
ohheycrypto/database/db.py
ohheycrypto/database/models.py
ohheycrypto/models/__init__.py
ohheycrypto/models/fee.py
ohheycrypto/models/order.py
ohheycrypto/models/price.py
ohheycrypto/monitoring/__init__.py
ohheycrypto/monitoring/metrics.py
ohheycrypto/plugins/__init__.py
ohheycrypto/plugins/discord.py
ohheycrypto/services/__init__.py
ohheycrypto/services/logging.py
ohheycrypto/services/market.py
ohheycrypto/services/wallet.py
ohheycrypto/utils/__init__.py
ohheycrypto/utils/retry.py
ohheycrypto/utils/shutdown.py
ohheycrypto-0.2.0.dist-info/licenses/LICENSE
ohheycrypto-0.2.0.dist-info/METADATA
ohheycrypto-0.2.0.dist-info/WHEEL
ohheycrypto-0.2.0.dist-info/entry_points.txt
ohheycrypto-0.2.0.dist-info/top_level.txt
ohheycrypto-0.2.0.dist-info/RECORD
