Metadata-Version: 2.4
Name: ohheycrypto
Version: 0.2.0
Summary: A sophisticated cryptocurrency trading bot with advanced technical analysis and risk management
Home-page: https://github.com/sn/ohheycrypto
Author: Sean Nieuwoudt
Author-email: Sean Nieuwoudt <sean@underwulf.com>
License: MIT License
Project-URL: Homepage, https://github.com/sn/ohheycrypto
Project-URL: Bug Tracker, https://github.com/sn/ohheycrypto/issues
Project-URL: Documentation, https://github.com/sn/ohheycrypto#readme
Project-URL: Source Code, https://github.com/sn/ohheycrypto
Keywords: cryptocurrency,trading,bot,binance,bitcoin,btc,technical-analysis,rsi
Classifier: Development Status :: 4 - Beta
Classifier: Intended Audience :: Financial and Insurance Industry
Classifier: Topic :: Office/Business :: Financial :: Investment
Classifier: License :: OSI Approved :: MIT License
Classifier: Programming Language :: Python :: 3
Classifier: Programming Language :: Python :: 3.11
Classifier: Programming Language :: Python :: 3.12
Classifier: Operating System :: OS Independent
Requires-Python: >=3.11
License-File: LICENSE
Requires-Dist: python-binance>=1.0.19
Requires-Dist: requests>=2.32.0
Requires-Dist: numpy>=2.0.0
Requires-Dist: pydantic>=2.0.0
Requires-Dist: yachalk>=0.1.5
Requires-Dist: psutil>=6.0.0
Provides-Extra: dev
Requires-Dist: pytest>=8.0.0; extra == "dev"
Requires-Dist: pytest-cov>=6.0.0; extra == "dev"
Requires-Dist: pytest-mock>=3.14.0; extra == "dev"
Requires-Dist: black>=24.0.0; extra == "dev"
Requires-Dist: flake8>=7.0.0; extra == "dev"
Requires-Dist: mypy>=1.0.0; extra == "dev"
Requires-Dist: isort>=5.13.0; extra == "dev"
Requires-Dist: bandit>=1.7.0; extra == "dev"
Requires-Dist: pre-commit>=4.0.0; extra == "dev"
Dynamic: author
Dynamic: home-page
Dynamic: license-file
Dynamic: requires-python
